flexrag/__init__.py
flexrag/assistant/__init__.py
flexrag/assistant/assistant.py
flexrag/assistant/basic_assistant.py
flexrag/assistant/chatqa_assistant.py
flexrag/assistant/document_chat_assistant.py
flexrag/assistant/modular_rag_assistant.py
flexrag/assistant/online_assistant.py
flexrag/assistant/assistant_prompts/longform_generate_prompt_with_context.json
flexrag/assistant/assistant_prompts/longform_generate_prompt_without_context.json
flexrag/assistant/assistant_prompts/shortform_generate_prompt_with_context.json
flexrag/assistant/assistant_prompts/shortform_generate_prompt_without_context.json
flexrag/chunking/__init__.py
flexrag/chunking/basic_chunkers.py
flexrag/chunking/chunker_base.py
flexrag/chunking/semantic_chunker.py
flexrag/chunking/sentence_splitter.py
flexrag/context_refine/__init__.py
flexrag/context_refine/arranger.py
flexrag/context_refine/refiner.py
flexrag/context_refine/summarizer.py
flexrag/database/__init__.py
flexrag/database/databsae_base.py
flexrag/database/lmdb_database.py
flexrag/database/naive_database.py
flexrag/database/serializer.py
flexrag/datasets/__init__.py
flexrag/datasets/dataset.py
flexrag/datasets/hf_dataset.py
flexrag/datasets/line_delimited_dataset.py
flexrag/datasets/rag_dataset.py
flexrag/datasets/retrieval_dataset.py
flexrag/document_parser/__init__.py
flexrag/document_parser/docling_parser.py
flexrag/document_parser/document_parser_base.py
flexrag/document_parser/markitdown_parser.py
flexrag/entrypoints/__init__.py
flexrag/entrypoints/add_index.py
flexrag/entrypoints/cache.py
flexrag/entrypoints/eval_assistant.py
flexrag/entrypoints/eval_retriever.py
flexrag/entrypoints/prepare_corpus.py
flexrag/entrypoints/prepare_retriever.py
flexrag/entrypoints/run_interactive.py
flexrag/entrypoints/serve_retriever.py
flexrag/entrypoints/assets/flexrag-wide.png
flexrag/entrypoints/assets/flexrag.png
flexrag/entrypoints/assets/robot.png
flexrag/entrypoints/assets/user.png
flexrag-0.3.0.dist-info/METADATA
flexrag-0.3.0.dist-info/WHEEL
flexrag-0.3.0.dist-info/top_level.txt
flexrag-0.3.0.dist-info/RECORD
flexrag-0.3.0.dist-info/licenses/LICENSE
