Metadata-Version: 2.4
Name: flexrag
Version: 0.3.0
Summary: Flexible RAG (Retrieval-Augmented Generation) framework for building AI applications.
Author-email: Zhang Zhuocheng <zhuocheng_zhang@outlook.com>
License: MIT License
Project-URL: Homepage, https://github.com/ictnlp/flexrag
Project-URL: Documentation, https://flexrag.readthedocs.io/en/latest/
Project-URL: Source, https://github.com/ictnlp/flexrag
Classifier: Development Status :: 3 - Alpha
Classifier: Intended Audience :: Developers
Classifier: License :: OSI Approved :: MIT License
Classifier: Operating System :: OS Independent
Classifier: Programming Language :: Python :: 3
Classifier: Programming Language :: Python :: 3.11
Classifier: Programming Language :: Python :: 3.12
Classifier: Programming Language :: Python :: 3.13
Classifier: Topic :: Scientific/Engineering :: Artificial Intelligence
Requires-Python: >=3.11
License-File: LICENSE
Requires-Dist: numpy
Requires-Dist: tenacity
Requires-Dist: hydra-core>=1.3
Requires-Dist: omegaconf>=2.3.0
Requires-Dist: pillow
Requires-Dist: colorama
Requires-Dist: torch==2.7.0
Requires-Dist: pandas
Requires-Dist: sentencepiece
Requires-Dist: rouge
Requires-Dist: sacrebleu>=2.4.2
Requires-Dist: pytrec_eval>=0.5
Requires-Dist: datasets>=3.2.0
Requires-Dist: openai>=1.58.1
Requires-Dist: anthropic
Requires-Dist: cohere
Requires-Dist: ollama
Requires-Dist: sentence_transformers
Requires-Dist: transformers>=4.52.3
Requires-Dist: accelerate
Requires-Dist: mixedbread
Requires-Dist: voyageai
Requires-Dist: lmdb
Requires-Dist: msgpack
Requires-Dist: unidecode
Requires-Dist: sacremoses
Requires-Dist: opencc
Requires-Dist: PyStemmer
Requires-Dist: bm25s
Requires-Dist: elasticsearch>=8.14.0
Requires-Dist: beautifulsoup4
Requires-Dist: typesense
Requires-Dist: httpx
Requires-Dist: scipy
Requires-Dist: scann>=1.4.0
Requires-Dist: duckduckgo_search
Requires-Dist: serpapi
Requires-Dist: pytest-playwright
Requires-Dist: markitdown
Requires-Dist: gradio>=5.8.0
Requires-Dist: regex
Requires-Dist: nltk
Requires-Dist: tiktoken
Provides-Extra: dev
Requires-Dist: black; extra == "dev"
Requires-Dist: pytest; extra == "dev"
Requires-Dist: pytest-asyncio; extra == "dev"
Requires-Dist: pytest-mock; extra == "dev"
Requires-Dist: sphinx; extra == "dev"
Requires-Dist: sphinx-autobuild; extra == "dev"
Requires-Dist: sphinx-book-theme; extra == "dev"
Requires-Dist: sphinx-copybutton; extra == "dev"
Requires-Dist: sphinx-intl; extra == "dev"
Requires-Dist: myst-parser; extra == "dev"
Requires-Dist: rstcheck; extra == "dev"
Requires-Dist: doc8; extra == "dev"
Requires-Dist: PySocks>=1.7.1; extra == "dev"
Requires-Dist: cibuildwheel; extra == "dev"
Dynamic: license-file
